BDMesh/Mesh1D.cp37-win_amd64.pyd
BDMesh/Mesh1D.pxd
BDMesh/Mesh1DUniform.cp37-win_amd64.pyd
BDMesh/Mesh1DUniform.pxd
BDMesh/TreeMesh1D.cp37-win_amd64.pyd
BDMesh/TreeMesh1D.pxd
BDMesh/TreeMesh1DUniform.cp37-win_amd64.pyd
BDMesh/TreeMesh1DUniform.pxd
BDMesh/__init__.py
BDMesh/_helpers.cp37-win_amd64.pyd
BDMesh/_version.py
BDMesh-0.2.18.dist-info/LICENSE.txt
BDMesh-0.2.18.dist-info/METADATA
BDMesh-0.2.18.dist-info/NOTICE.txt
BDMesh-0.2.18.dist-info/WHEEL
BDMesh-0.2.18.dist-info/top_level.txt
BDMesh-0.2.18.dist-info/RECORD
