Metadata-Version: 2.1
Name: BDMesh
Version: 0.2.18
Summary: BD Mesh generator
Home-page: https://github.com/bond-anton/BDMesh
Author: Anton Bondarenko
Author-email: bond.anton@gmail.com
License: Apache Software License
